mspeeps/__init__.py
mspeeps/cli.py
mspeeps/core.py
mspeeps/formula_matching.py
mspeeps/utils.py
mspeeps-0.1.3.dist-info/licenses/LICENSE
mspeeps-0.1.3.dist-info/METADATA
mspeeps-0.1.3.dist-info/WHEEL
mspeeps-0.1.3.dist-info/entry_points.txt
mspeeps-0.1.3.dist-info/top_level.txt
mspeeps-0.1.3.dist-info/RECORD
