Metadata-Version: 2.4
Name: mspeeps
Version: 0.1.3
Summary: A Python package for extracting mass spectrometry spectra from mzML files and converting them to MSP format
Author-email: Gabriel Reder <gk@reder.io>
License: MIT
Project-URL: Homepage, https://github.com/gkreder/mspeeps
Project-URL: Bug Tracker, https://github.com/gkreder/mspeeps/issues
Keywords: mass spectrometry,mzML,MSP,spectrum,chemistry
Classifier: Programming Language :: Python :: 3
Classifier: Programming Language :: Python :: 3.12
Classifier: License :: OSI Approved :: MIT License
Classifier: Operating System :: OS Independent
Classifier: Topic :: Scientific/Engineering :: Chemistry
Classifier: Topic :: Scientific/Engineering :: Bio-Informatics
Requires-Python: >=3.10
License-File: LICENSE
Requires-Dist: pandas<3,>=2.2.3
Requires-Dist: pymzml<3,>=2.5.11
Requires-Dist: rdkit<2025,>=2024.9.6
Requires-Dist: openpyxl<4,>=3.1.5
Requires-Dist: fragfit<0.2,>=0.1.2
Requires-Dist: numpy>=1.26.0
Provides-Extra: dev
Requires-Dist: pytest>=7.0.0; extra == "dev"
Requires-Dist: pytest-cov>=4.0.0; extra == "dev"
Requires-Dist: black>=23.0.0; extra == "dev"
Requires-Dist: isort>=5.0.0; extra == "dev"
Requires-Dist: mypy>=1.0.0; extra == "dev"
Dynamic: license-file
